nextcloud_news_filter-0.2.0.dist-info/METADATA
nextcloud_news_filter-0.2.0.dist-info/WHEEL
nextcloud_news_filter-0.2.0.dist-info/entry_points.txt
nextcloud_news_filter-0.2.0.dist-info/licenses/LICENSE
nextcloud_news_filter/__init__.py
nextcloud_news_filter/cli.py
nextcloud_news_filter/config.py
nextcloud_news_filter/filter.py
nextcloud_news_filter/model.py
nextcloud_news_filter/py.typed
nextcloud_news_filter-0.2.0.dist-info/RECORD
