Metadata-Version: 2.1
Name: nextcloud_news_filter
Version: 0.2.0
Summary: Small library to filter Nextcloud News feeds
Author-Email: Lioman <dev@lioman.de>
License: GPL-3.0-later
Classifier: Programming Language :: Python :: 3
Classifier: Programming Language :: Python :: 3.11
Classifier: Programming Language :: Python :: 3.12
Classifier: Development Status :: 4 - Beta
Classifier: Environment :: Console
Classifier: Environment :: Web Environment
Classifier: Topic :: Internet :: WWW/HTTP :: Dynamic Content :: News/Diary
Project-URL: Source, https://gitlab.com/lioman/nextcloud_news_filter
Project-URL: Issue tracker, https://gitlab.com/lioman/nextcloud_news_filter/-/issues
Project-URL: Changelog, https://gitlab.com/lioman/nextcloud_news_filter/-/blob/main/CHANGELOG.md
Requires-Python: <3.12,>=3.10
Requires-Dist: httpx[http2]>=0.27.0
Requires-Dist: typer>0.8.0; extra == "cli"
Provides-Extra: cli
